hostchk/__init__.py
hostchk/__main__.py
hostchk/_version.py
hostchk/hostchk.py
hostchk-1.1.6.dist-info/AUTHORS.rst
hostchk-1.1.6.dist-info/LICENSE
hostchk-1.1.6.dist-info/METADATA
hostchk-1.1.6.dist-info/WHEEL
hostchk-1.1.6.dist-info/entry_points.txt
hostchk-1.1.6.dist-info/top_level.txt
hostchk-1.1.6.dist-info/RECORD
