Metadata-Version: 2.1
Name: hostchk
Version: 1.1.6
Summary: A command-line tool for checking HTTP status codes and  server response headers of URLs
Home-page: https://github.com/brigxt0/hostchk/
Author: brigxt0 (◣_◢)ⱤEViⱠ(◣_◢)
License: MIT license
Keywords: hostchk site management www http link check
Platform: UNKNOWN
Classifier: Development Status :: 3 - Alpha
Classifier: Environment :: Console
Classifier: Intended Audience :: Developers
Classifier: Programming Language :: Python :: 3
Classifier: Programming Language :: Python :: 3.4
Classifier: Programming Language :: Python :: 3.5
Classifier: Programming Language :: Python :: 3.6
Classifier: Programming Language :: Python :: 3.7
Classifier: Programming Language :: Python :: 3.8
Classifier: Programming Language :: Python :: Implementation :: CPython
Classifier: Topic :: Internet :: WWW/HTTP
Classifier: Topic :: Internet :: WWW/HTTP :: Site Management
Classifier: Topic :: Internet :: WWW/HTTP :: Site Management :: Link Checking
Classifier: Intended Audience :: Developers
Classifier: Intended Audience :: System Administrators
Requires-Python: >=3.7, <4
License-File: LICENSE
License-File: AUTHORS.rst
Requires-Dist: requests (==2.26.0)
Requires-Dist: rich (==12.0.1)
Requires-Dist: tqdm (==4.62.3)
Requires-Dist: urllib3 (==1.26.7)
